regexa/__init__.py
regexa/regexa.py
regexa-0.1.1.dist-info/LICENSE
regexa-0.1.1.dist-info/METADATA
regexa-0.1.1.dist-info/WHEEL
regexa-0.1.1.dist-info/top_level.txt
regexa-0.1.1.dist-info/RECORD
