Metadata-Version: 2.1
Name: regexa
Version: 0.1.1
Summary: A modern, full-featured regex library for Python
Home-page: https://github.com/bri-anadi/regexa
Author: Brian Adi
Author-email: uix.brianadi@gmail.com
License: UNKNOWN
Keywords: regex,regular expressions,text processing,validation
Platform: UNKNOWN
Classifier: Development Status :: 4 - Beta
Classifier: Intended Audience :: Developers
Classifier: License :: OSI Approved :: MIT License
Classifier: Programming Language :: Python :: 3
Classifier: Programming Language :: Python :: 3.6
Classifier: Programming Language :: Python :: 3.7
Classifier: Programming Language :: Python :: 3.8
Classifier: Programming Language :: Python :: 3.9
Classifier: Topic :: Software Development :: Libraries :: Python Modules
Classifier: Topic :: Text Processing :: General
Requires-Python: >=3.6
